nptab/__init__.py
nptab/_version.py
nptab/git_version.py
nptab/hashjoin.py
nptab/nptab.py
nptab/numpy_types.py
nptab/util.py
nptab-3.0.0.dist-info/LICENSE
nptab-3.0.0.dist-info/METADATA
nptab-3.0.0.dist-info/WHEEL
nptab-3.0.0.dist-info/top_level.txt
nptab-3.0.0.dist-info/RECORD
