Metadata-Version: 2.1
Name: nptab
Version: 3.0.0
Summary: SQL atop numpy arrays represented as tables. Tables logic forked from github.com/BastiaanBergman/nptab
Home-page: https://github.com/javadba/nptab
Author: Stephen Boesch
Author-email: javadba@gmail.com
License: MIT
Project-URL: Source Code, https://github.com/javadba/nptab
Keywords: numpy sql table
Platform: UNKNOWN
Classifier: Programming Language :: Python :: 3.8
Classifier: Programming Language :: Python :: 3.7
Classifier: License :: OSI Approved :: MIT License
Classifier: Operating System :: OS Independent
Requires-Python: >=3.7
Requires-Dist: numpy
Requires-Dist: tabulate
